resources/__init__.py
Fexr-0.0.1.dist-info/LICENSE
Fexr-0.0.1.dist-info/METADATA
Fexr-0.0.1.dist-info/WHEEL
Fexr-0.0.1.dist-info/top_level.txt
Fexr-0.0.1.dist-info/RECORD
