Metadata-Version: 2.1
Name: Fexr
Version: 0.0.1
Summary: REST Client for Fexr
Home-page: https://github.com/fexrapis/pyfexr
Author: Fexr
Author-email: nidhin@getfexr.com
License: UNKNOWN
Project-URL: Bug Tracker, https://github.com/fexrapis/pyfexr/issues
Platform: UNKNOWN
Classifier: Programming Language :: Python :: 3
Classifier: License :: OSI Approved :: MIT License
Classifier: Operating System :: OS Independent
Requires-Python: >=3.6
License-File: LICENSE
